{
    "products": [
        {
            "linen-curtains": {
                "name": "",
                "price": "",
                "description": "",
                "imageUrl": "",
                "sizes": [
                    {
                        "size": "",
                        "price": ""
                    }
                ],
                "colours": [
                    {
                        "colour": ""
                    }
                ],
                "large-images": [
                    {
                        "url": ""
                    }
                ],
                "link": ""
            }
        },
        {
            "linen-bedding": {
                "category-title": "",
                "category-desc": "",
                "products": [
                    {
                        "name": "",
                        "price": "",
                        "imageUrl": "",
                        "large-images": [
                            {
                                "url": ""
                            }
                        ],
                        "link": ""
                    }
                ]
            }
        },
        {
            "living": {
                "category-title": "",
                "category-desc": "",
                "products": [
                    {
                        "name": "",
                        "price": "",
                        "imageUrl": "",
                        "large-images": [
                            {
                                "url": ""
                            }
                        ],
                        "link": ""
                    }
                ]
            }
        }
    ]
}
